neural_compressor/__init__.py
neural_compressor/config.py
neural_compressor/mix_precision.py
neural_compressor/objective.py
neural_compressor/quantization.py
neural_compressor/training.py
neural_compressor/version.py
neural_compressor/adaptor/__init__.py
neural_compressor/adaptor/adaptor.py
neural_compressor/adaptor/keras.py
neural_compressor/adaptor/keras.yaml
neural_compressor/adaptor/onnxrt.py
neural_compressor/adaptor/onnxrt.yaml
neural_compressor/adaptor/onnxrt_cuda.yaml
neural_compressor/adaptor/onnxrt_dml.yaml
neural_compressor/adaptor/onnxrt_dnnl.yaml
neural_compressor/adaptor/onnxrt_trt.yaml
neural_compressor/adaptor/pytorch.py
neural_compressor/adaptor/pytorch_cpu.yaml
neural_compressor/adaptor/pytorch_gpu.yaml
neural_compressor/adaptor/pytorch_ipex.yaml
neural_compressor/adaptor/query.py
neural_compressor/adaptor/tensorflow.py
neural_compressor/adaptor/tensorflow.yaml
neural_compressor/adaptor/tensorflow_itex.yaml
neural_compressor/adaptor/keras_utils/__init__.py
neural_compressor/adaptor/keras_utils/conv2d.py
neural_compressor/adaptor/keras_utils/dense.py
neural_compressor/adaptor/keras_utils/depthwise_conv2d.py
neural_compressor/adaptor/keras_utils/pool2d.py
neural_compressor/adaptor/keras_utils/quantizer.py
neural_compressor/adaptor/keras_utils/separable_conv2d.py
neural_compressor/adaptor/ox_utils/__init__.py
neural_compressor/adaptor/ox_utils/calibration.py
neural_compressor/adaptor/ox_utils/calibrator.py
neural_compressor/adaptor/ox_utils/quantizer.py
neural_compressor/adaptor/ox_utils/smooth_quant.py
neural_compressor/adaptor/ox_utils/util.py
neural_compressor/adaptor/ox_utils/weight_only.py
neural_compressor/adaptor/ox_utils/operators/__init__.py
neural_compressor/adaptor/ox_utils/operators/activation.py
neural_compressor/adaptor/ox_utils/operators/argmax.py
neural_compressor/adaptor/ox_utils/operators/attention.py
neural_compressor/adaptor/ox_utils/operators/binary_op.py
neural_compressor/adaptor/ox_utils/operators/concat.py
neural_compressor-3.7.1.dist-info/LICENSE
neural_compressor-3.7.1.dist-info/METADATA
neural_compressor-3.7.1.dist-info/WHEEL
neural_compressor-3.7.1.dist-info/third-party-programs.txt
neural_compressor-3.7.1.dist-info/top_level.txt
neural_compressor-3.7.1.dist-info/RECORD
