Metadata-Version: 2.1
Name: neural_compressor
Version: 3.7.1
Summary: Repository of Intel® Neural Compressor
Home-page: https://github.com/intel/neural-compressor
Author: Intel AIPT Team
Author-email: feng.tian@intel.com, haihao.shen@intel.com, suyue.chen@intel.com
License: Apache 2.0
Keywords: quantization,auto-tuning,post-training static quantization,post-training dynamic quantization,quantization-aware training
Classifier: Intended Audience :: Science/Research
Classifier: Programming Language :: Python :: 3
Classifier: Topic :: Scientific/Engineering :: Artificial Intelligence
Classifier: License :: OSI Approved :: Apache Software License
Requires-Python: >=3.7.0
License-File: LICENSE
License-File: third-party-programs.txt
Requires-Dist: deprecated>=1.2.13
Requires-Dist: numpy<2.0
Requires-Dist: opencv-python-headless
Requires-Dist: pandas
Requires-Dist: Pillow
Requires-Dist: prettytable
Requires-Dist: psutil
Requires-Dist: py-cpuinfo
Requires-Dist: pyyaml
Requires-Dist: requests
Requires-Dist: schema
Requires-Dist: scikit-learn
Requires-Dist: pycocotools; sys_platform != "win32" or python_version > "3.8"
Requires-Dist: pycocotools-windows; sys_platform == "win32" and python_version <= "3.8"
Provides-Extra: pt
Requires-Dist: numpy; extra == "pt"
Requires-Dist: prettytable; extra == "pt"
Requires-Dist: psutil; extra == "pt"
Requires-Dist: py-cpuinfo; extra == "pt"
Requires-Dist: pydantic; extra == "pt"
Provides-Extra: tf
Requires-Dist: prettytable; extra == "tf"
Requires-Dist: psutil; extra == "tf"
Requires-Dist: py-cpuinfo; extra == "tf"
Requires-Dist: pydantic; extra == "tf"
Requires-Dist: pyyaml; extra == "tf"
Requires-Dist: tensorflow; extra == "tf"
